[
  {
    "waktu": "2019-01-01 07:00",
    "suhu": "25.077",
    "kelembapan": "1.141",
    "intensitas": "221.633",
    "daya": 42.192050359026304,
    "tegangan": 13.973718906357837,
    "arus": 2.9615872786891613
  },
  {
    "waktu": "2019-01-01 08:00",
    "suhu": "25.741",
    "kelembapan": "1.139",
    "intensitas": "389.842",
    "daya": 44.23158719315656,
    "tegangan": 16.461953127519156,
    "arus": 2.507081233991279
  },
  {
    "waktu": "2019-01-01 09:00",
    "suhu": "26.335",
    "kelembapan": "1.138",
    "intensitas": "550.792",
    "daya": 40.20014412800393,
    "tegangan": 16.439281481484294,
    "arus": 2.0383749469813197
  },
  {
    "waktu": "2019-01-01 10:00",
    "suhu": "26.774",
    "kelembapan": "1.136",
    "intensitas": "647.679",
    "daya": 41.92355022395555,
    "tegangan": 17.34110020348379,
    "arus": 1.9588070182436799
  },
  {
    "waktu": "2019-01-01 11:00",
    "suhu": "26.986",
    "kelembapan": "1.135",
    "intensitas": "709.526",
    "daya": 44.03138783729945,
    "tegangan": 17.762099373889946,
    "arus": 2.199427004829221
  },
  {
    "waktu": "2019-01-01 12:00",
    "suhu": "27.043",
    "kelembapan": "1.133",
    "intensitas": "715.997",
    "daya": 43.67570515772268,
    "tegangan": 16.985813356677163,
    "arus": 2.414671283239435
  },
  {
    "waktu": "2019-01-01 13:00",
    "suhu": "26.968",
    "kelembapan": "1.133",
    "intensitas": "672.070",
    "daya": 40.726231656176445,
    "tegangan": 16.714698882733828,
    "arus": 1.9930075656090087
  },
  {
    "waktu": "2019-01-01 14:00",
    "suhu": "26.706",
    "kelembapan": "1.133",
    "intensitas": "547.977",
    "daya": 42.96474382781441,
    "tegangan": 16.767915688581343,
    "arus": 2.4321948361541716
  },
  {
    "waktu": "2019-01-01 15:00",
    "suhu": "26.429",
    "kelembapan": "1.133",
    "intensitas": "413.109",
    "daya": 41.52632461900864,
    "tegangan": 16.417687225315184,
    "arus": 2.3743670418021887
  },
  {
    "waktu": "2019-01-01 16:00",
    "suhu": "26.107",
    "kelembapan": "1.134",
    "intensitas": "247.849",
    "daya": 40.92696013572673,
    "tegangan": 16.972634148231933,
    "arus": 2.3815935702004567
  },
  {
    "waktu": "2019-01-01 17:00",
    "suhu": "25.667",
    "kelembapan": "1.136",
    "intensitas": "81.603",
    "daya": 44.0924704966356,
    "tegangan": 16.5340024633349,
    "arus": 2.518978911200309
  },
  {
    "waktu": "2019-01-01 18:00",
    "suhu": "25.280",
    "kelembapan": "1.137",
    "intensitas": "2.360",
    "daya": 41.55263993046198,
    "tegangan": 0,
    "arus": 0
  },
  {
    "waktu": "2019-01-01 19:00",
    "suhu": "25.118",
    "kelembapan": "1.138",
    "intensitas": "0",
    "daya": 41.09944596100445,
    "tegangan": 0,
    "arus": 0
  },
  {
    "waktu": "2019-01-01 20:00",
    "suhu": "25.028",
    "kelembapan": "1.139",
    "intensitas": "0",
    "daya": 43.32041315084102,
    "tegangan": 0,
    "arus": 0
  },
  {
    "waktu": "2019-01-01 21:00",
    "suhu": "24.900",
    "kelembapan": "1.140",
    "intensitas": "0",
    "daya": 41.705893141013746,
    "tegangan": 0,
    "arus": 0
  },
  {
    "waktu": "2019-01-01 22:00",
    "suhu": "24.779",
    "kelembapan": "1.140",
    "intensitas": "0",
    "daya": 44.139314402641745,
    "tegangan": 0,
    "arus": 0
  },
  {
    "waktu": "2019-01-01 23:00",
    "suhu": "24.668",
    "kelembapan": "1.140",
    "intensitas": "0",
    "daya": 41.8145238430472,
    "tegangan": 0,
    "arus": 0
  },
  {
    "waktu": "2019-01-02 00:00",
    "suhu": "24.574",
    "kelembapan": "1.140",
    "intensitas": "0",
    "daya": 40.777038728711375,
    "tegangan": 0,
    "arus": 0
  },
  {
    "waktu": "2019-01-02 01:00",
    "suhu": "24.436",
    "kelembapan": "1.140",
    "intensitas": "0",
    "daya": 41.91551870023166,
    "tegangan": 0,
    "arus": 0
  },
  {
    "waktu": "2019-01-02 02:00",
    "suhu": "24.297",
    "kelembapan": "1.140",
    "intensitas": "0",
    "daya": 40.24742143564229,
    "tegangan": 0,
    "arus": 0
  },
  {
    "waktu": "2019-01-02 03:00",
    "suhu": "24.201",
    "kelembapan": "1.140",
    "intensitas": "0",
    "daya": 41.41725131812633,
    "tegangan": 0,
    "arus": 0
  },
  {
    "waktu": "2019-01-02 04:00",
    "suhu": "24.105",
    "kelembapan": "1.141",
    "intensitas": "0",
    "daya": 42.18862784144082,
    "tegangan": 0,
    "arus": 0
  },
  {
    "waktu": "2019-01-02 05:00",
    "suhu": "24.034",
    "kelembapan": "1.142",
    "intensitas": "0",
    "daya": 44.56271458652338,
    "tegangan": 0,
    "arus": 0
  },
  {
    "waktu": "2019-01-02 06:00",
    "suhu": "24.235",
    "kelembapan": "1.143",
    "intensitas": "36.078",
    "daya": 40.13582028309273,
    "tegangan": 0,
    "arus": 0
  },
  {
    "waktu": "2019-01-02 07:00",
    "suhu": "24.874",
    "kelembapan": "1.142",
    "intensitas": "173.587",
    "daya": 40.889602161224396,
    "tegangan": 13.428208980198232,
    "arus": 2.701874770618647
  },
  {
    "waktu": "2019-01-02 08:00",
    "suhu": "25.442",
    "kelembapan": "1.141",
    "intensitas": "335.198",
    "daya": 41.21728538645327,
    "tegangan": 16.08743805043528,
    "arus": 2.3927071341278436
  },
  {
    "waktu": "2019-01-02 09:00",
    "suhu": "25.972",
    "kelembapan": "1.139",
    "intensitas": "502.538",
    "daya": 42.58730278508523,
    "tegangan": 16.185711859385336,
    "arus": 2.456346733333117
  },
  {
    "waktu": "2019-01-02 10:00",
    "suhu": "26.414",
    "kelembapan": "1.138",
    "intensitas": "630.545",
    "daya": 40.17771273635269,
    "tegangan": 17.650688882005927,
    "arus": 2.24187868287168
  },
  {
    "waktu": "2019-01-02 11:00",
    "suhu": "26.639",
    "kelembapan": "1.136",
    "intensitas": "712.418",
    "daya": 44.92028254291105,
    "tegangan": 17.969633110931916,
    "arus": 2.333991205599279
  },
  {
    "waktu": "2019-01-02 12:00",
    "suhu": "26.712",
    "kelembapan": "1.135",
    "intensitas": "746.832",
    "daya": 40.8352109931873,
    "tegangan": 16.3214824406545,
    "arus": 2.369564852083937
  },
  {
    "waktu": "2019-01-02 13:00",
    "suhu": "26.711",
    "kelembapan": "1.134",
    "intensitas": "723.141",
    "daya": 42.796560499020245,
    "tegangan": 16.43382227596805,
    "arus": 2.2548133590083137
  },
  {
    "waktu": "2019-01-02 14:00",
    "suhu": "26.640",
    "kelembapan": "1.134",
    "intensitas": "644.238",
    "daya": 44.24390078661085,
    "tegangan": 16.903931087345004,
    "arus": 2.3805963874360474
  },
  {
    "waktu": "2019-01-02 15:00",
    "suhu": "26.446",
    "kelembapan": "1.134",
    "intensitas": "505.272",
    "daya": 40.63702091297386,
    "tegangan": 16.536887623759046,
    "arus": 2.218070952731916
  },
  {
    "waktu": "2019-01-02 16:00",
    "suhu": "26.080",
    "kelembapan": "1.136",
    "intensitas": "302.817",
    "daya": 43.630610876877874,
    "tegangan": 16.174489967429576,
    "arus": 2.6782572217670957
  },
  {
    "waktu": "2019-01-02 17:00",
    "suhu": "25.558",
    "kelembapan": "1.137",
    "intensitas": "106.376",
    "daya": 41.77700549256139,
    "tegangan": 16.440687434723813,
    "arus": 2.144705572419234
  },
  {
    "waktu": "2019-01-02 18:00",
    "suhu": "24.906",
    "kelembapan": "1.139",
    "intensitas": "3.393",
    "daya": 41.64738829823184,
    "tegangan": 0,
    "arus": 0
  },
  {
    "waktu": "2019-01-02 19:00",
    "suhu": "24.644",
    "kelembapan": "1.140",
    "intensitas": "0",
    "daya": 41.886731978029225,
    "tegangan": 0,
    "arus": 0
  },
  {
    "waktu": "2019-01-02 20:00",
    "suhu": "24.478",
    "kelembapan": "1.141",
    "intensitas": "0",
    "daya": 43.323242438265105,
    "tegangan": 0,
    "arus": 0
  },
  {
    "waktu": "2019-01-02 21:00",
    "suhu": "24.337",
    "kelembapan": "1.142",
    "intensitas": "0",
    "daya": 40.48862625782256,
    "tegangan": 0,
    "arus": 0
  },
  {
    "waktu": "2019-01-02 22:00",
    "suhu": "24.204",
    "kelembapan": "1.142",
    "intensitas": "0",
    "daya": 41.879880323806894,
    "tegangan": 0,
    "arus": 0
  },
  {
    "waktu": "2019-01-02 23:00",
    "suhu": "24.087",
    "kelembapan": "1.141",
    "intensitas": "0",
    "daya": 42.53243444620528,
    "tegangan": 0,
    "arus": 0
  },
  {
    "waktu": "2019-01-03 00:00",
    "suhu": "23.981",
    "kelembapan": "1.141",
    "intensitas": "0",
    "daya": 40.794966689184704,
    "tegangan": 0,
    "arus": 0
  },
  {
    "waktu": "2019-01-03 01:00",
    "suhu": "23.931",
    "kelembapan": "1.140",
    "intensitas": "0",
    "daya": 44.679451749070736,
    "tegangan": 0,
    "arus": 0
  },
  {
    "waktu": "2019-01-03 02:00",
    "suhu": "23.962",
    "kelembapan": "1.140",
    "intensitas": "0",
    "daya": 44.12555818474788,
    "tegangan": 0,
    "arus": 0
  },
  {
    "waktu": "2019-01-03 03:00",
    "suhu": "24.053",
    "kelembapan": "1.139",
    "intensitas": "0",
    "daya": 43.02593865957127,
    "tegangan": 0,
    "arus": 0
  },
  {
    "waktu": "2019-01-03 04:00",
    "suhu": "24.122",
    "kelembapan": "1.139",
    "intensitas": "0",
    "daya": 42.20358265802111,
    "tegangan": 0,
    "arus": 0
  },
  {
    "waktu": "2019-01-03 05:00",
    "suhu": "24.236",
    "kelembapan": "1.140",
    "intensitas": "0",
    "daya": 43.72515161643046,
    "tegangan": 0,
    "arus": 0
  },
  {
    "waktu": "2019-01-03 06:00",
    "suhu": "24.493",
    "kelembapan": "1.140",
    "intensitas": "25.893",
    "daya": 42.361223526658115,
    "tegangan": 0,
    "arus": 0
  },
  {
    "waktu": "2019-01-03 07:00",
    "suhu": "25.085",
    "kelembapan": "1.140",
    "intensitas": "114.947",
    "daya": 41.894871982179815,
    "tegangan": 13.912193291071185,
    "arus": 2.629230849360306
  },
  {
    "waktu": "2019-01-03 08:00",
    "suhu": "25.523",
    "kelembapan": "1.140",
    "intensitas": "242.326",
    "daya": 40.85223436719198,
    "tegangan": 16.454100681565517,
    "arus": 2.0669318676872965
  },
  {
    "waktu": "2019-01-03 09:00",
    "suhu": "25.898",
    "kelembapan": "1.139",
    "intensitas": "403.471",
    "daya": 40.69278628488296,
    "tegangan": 16.9337507600991,
    "arus": 2.311837034332071
  },
  {
    "waktu": "2019-01-03 10:00",
    "suhu": "26.303",
    "kelembapan": "1.138",
    "intensitas": "563.413",
    "daya": 42.756305515375665,
    "tegangan": 17.18852872583521,
    "arus": 2.4579612156654065
  },
  {
    "waktu": "2019-01-03 11:00",
    "suhu": "26.622",
    "kelembapan": "1.136",
    "intensitas": "654.649",
    "daya": 40.74415510815711,
    "tegangan": 17.238568553740095,
    "arus": 2.0978309159022164
  },
  {
    "waktu": "2019-01-03 12:00",
    "suhu": "26.805",
    "kelembapan": "1.135",
    "intensitas": "697.052",
    "daya": 41.37668427870431,
    "tegangan": 16.545766266878797,
    "arus": 2.181384849526295
  },
  {
    "waktu": "2019-01-03 13:00",
    "suhu": "26.832",
    "kelembapan": "1.134",
    "intensitas": "671.925",
    "daya": 44.3288677688418,
    "tegangan": 16.32753636593532,
    "arus": 2.326064518222017
  },
  {
    "waktu": "2019-01-03 14:00",
    "suhu": "26.724",
    "kelembapan": "1.134",
    "intensitas": "588.778",
    "daya": 43.97881589700206,
    "tegangan": 16.288693221896303,
    "arus": 2.471385166835944
  },
  {
    "waktu": "2019-01-03 15:00",
    "suhu": "26.480",
    "kelembapan": "1.134",
    "intensitas": "450.509",
    "daya": 40.59082158521446,
    "tegangan": 16.03876416509589,
    "arus": 2.107030026221831
  },
  {
    "waktu": "2019-01-03 16:00",
    "suhu": "26.112",
    "kelembapan": "1.135",
    "intensitas": "278.079",
    "daya": 40.50528155819373,
    "tegangan": 16.32113320525384,
    "arus": 2.3492625738969273
  },
  {
    "waktu": "2019-01-03 17:00",
    "suhu": "25.617",
    "kelembapan": "1.137",
    "intensitas": "97.300",
    "daya": 42.2074504962745,
    "tegangan": 16.697216093857197,
    "arus": 2.4055522297650587
  },
  {
    "waktu": "2019-01-03 18:00",
    "suhu": "25.044",
    "kelembapan": "1.139",
    "intensitas": "2.995",
    "daya": 40.16407937861983,
    "tegangan": 0,
    "arus": 0
  },
  {
    "waktu": "2019-01-03 19:00",
    "suhu": "24.798",
    "kelembapan": "1.140",
    "intensitas": "0",
    "daya": 44.69138906989848,
    "tegangan": 0,
    "arus": 0
  },
  {
    "waktu": "2019-01-03 20:00",
    "suhu": "24.672",
    "kelembapan": "1.141",
    "intensitas": "0",
    "daya": 43.67862836469264,
    "tegangan": 0,
    "arus": 0
  },
  {
    "waktu": "2019-01-03 21:00",
    "suhu": "24.570",
    "kelembapan": "1.141",
    "intensitas": "0",
    "daya": 40.69990805972825,
    "tegangan": 0,
    "arus": 0
  },
  {
    "waktu": "2019-01-03 22:00",
    "suhu": "24.485",
    "kelembapan": "1.141",
    "intensitas": "0",
    "daya": 40.86993646897236,
    "tegangan": 0,
    "arus": 0
  },
  {
    "waktu": "2019-01-03 23:00",
    "suhu": "24.380",
    "kelembapan": "1.141",
    "intensitas": "0",
    "daya": 43.84256469990759,
    "tegangan": 0,
    "arus": 0
  },
  {
    "waktu": "2019-01-04 00:00",
    "suhu": "24.280",
    "kelembapan": "1.141",
    "intensitas": "0",
    "daya": 41.180028217763876,
    "tegangan": 0,
    "arus": 0
  },
  {
    "waktu": "2019-01-04 01:00",
    "suhu": "24.182",
    "kelembapan": "1.140",
    "intensitas": "0",
    "daya": 43.45625536547426,
    "tegangan": 0,
    "arus": 0
  },
  {
    "waktu": "2019-01-04 02:00",
    "suhu": "24.101",
    "kelembapan": "1.140",
    "intensitas": "0",
    "daya": 41.8733458673989,
    "tegangan": 0,
    "arus": 0
  },
  {
    "waktu": "2019-01-04 03:00",
    "suhu": "24.034",
    "kelembapan": "1.140",
    "intensitas": "0",
    "daya": 42.12362141265919,
    "tegangan": 0,
    "arus": 0
  },
  {
    "waktu": "2019-01-04 04:00",
    "suhu": "23.970",
    "kelembapan": "1.140",
    "intensitas": "0",
    "daya": 44.97276056043136,
    "tegangan": 0,
    "arus": 0
  },
  {
    "waktu": "2019-01-04 05:00",
    "suhu": "23.933",
    "kelembapan": "1.141",
    "intensitas": "0",
    "daya": 44.008310658625724,
    "tegangan": 0,
    "arus": 0
  },
  {
    "waktu": "2019-01-04 06:00",
    "suhu": "24.222",
    "kelembapan": "1.142",
    "intensitas": "48.721",
    "daya": 44.09390740614061,
    "tegangan": 0,
    "arus": 0
  },
  {
    "waktu": "2019-01-04 07:00",
    "suhu": "24.970",
    "kelembapan": "1.142",
    "intensitas": "219.761",
    "daya": 44.630274143309556,
    "tegangan": 13.118499533680094,
    "arus": 3.3203034577751653
  },
  {
    "waktu": "2019-01-04 08:00",
    "suhu": "25.506",
    "kelembapan": "1.141",
    "intensitas": "437.094",
    "daya": 40.62409112344939,
    "tegangan": 16.228190070136684,
    "arus": 2.1468123369095737
  },
  {
    "waktu": "2019-01-04 09:00",
    "suhu": "26.315",
    "kelembapan": "1.139",
    "intensitas": "668.493",
    "daya": 43.752573907380565,
    "tegangan": 16.454341293735062,
    "arus": 2.2459248168567445
  },
  {
    "waktu": "2019-01-04 10:00",
    "suhu": "26.964",
    "kelembapan": "1.137",
    "intensitas": "838.873",
    "daya": 44.117050443369976,
    "tegangan": 17.166432520291387,
    "arus": 2.0825119866588757
  },
  {
    "waktu": "2019-01-04 11:00",
    "suhu": "27.382",
    "kelembapan": "1.135",
    "intensitas": "927.162",
    "daya": 42.75923154851751,
    "tegangan": 17.844192466138093,
    "arus": 2.1116047095599866
  },
  {
    "waktu": "2019-01-04 12:00",
    "suhu": "27.613",
    "kelembapan": "1.133",
    "intensitas": "954.013",
    "daya": 40.59678157601747,
    "tegangan": 16.991455608461894,
    "arus": 2.1009513037525087
  },
  {
    "waktu": "2019-01-04 13:00",
    "suhu": "27.646",
    "kelembapan": "1.132",
    "intensitas": "899.931",
    "daya": 42.20537192800319,
    "tegangan": 16.340865815152384,
    "arus": 2.1542211832467633
  },
  {
    "waktu": "2019-01-04 14:00",
    "suhu": "27.544",
    "kelembapan": "1.131",
    "intensitas": "781.556",
    "daya": 44.27729030792612,
    "tegangan": 16.010604025435168,
    "arus": 2.479945763996119
  },
  {
    "waktu": "2019-01-04 15:00",
    "suhu": "27.289",
    "kelembapan": "1.131",
    "intensitas": "599.480",
    "daya": 43.345198770433996,
    "tegangan": 16.137505424336737,
    "arus": 2.641759882857641
  },
  {
    "waktu": "2019-01-04 16:00",
    "suhu": "26.914",
    "kelembapan": "1.132",
    "intensitas": "374.548",
    "daya": 41.840492141612664,
    "tegangan": 16.823283148166002,
    "arus": 2.4271508973801366
  },
  {
    "waktu": "2019-01-04 17:00",
    "suhu": "26.333",
    "kelembapan": "1.133",
    "intensitas": "132.941",
    "daya": 42.24062785235821,
    "tegangan": 16.89562648969071,
    "arus": 2.4920091692272837
  },
  {
    "waktu": "2019-01-04 18:00",
    "suhu": "25.579",
    "kelembapan": "1.135",
    "intensitas": "4.213",
    "daya": 41.71491605849461,
    "tegangan": 0,
    "arus": 0
  },
  {
    "waktu": "2019-01-04 19:00",
    "suhu": "25.254",
    "kelembapan": "1.137",
    "intensitas": "0",
    "daya": 44.02785576377037,
    "tegangan": 0,
    "arus": 0
  },
  {
    "waktu": "2019-01-04 20:00",
    "suhu": "25.129",
    "kelembapan": "1.138",
    "intensitas": "0",
    "daya": 40.43910715626615,
    "tegangan": 0,
    "arus": 0
  },
  {
    "waktu": "2019-01-04 21:00",
    "suhu": "24.997",
    "kelembapan": "1.138",
    "intensitas": "0",
    "daya": 40.833278863965525,
    "tegangan": 0,
    "arus": 0
  },
  {
    "waktu": "2019-01-04 22:00",
    "suhu": "24.847",
    "kelembapan": "1.138",
    "intensitas": "0",
    "daya": 41.739897368895114,
    "tegangan": 0,
    "arus": 0
  },
  {
    "waktu": "2019-01-04 23:00",
    "suhu": "24.678",
    "kelembapan": "1.139",
    "intensitas": "0",
    "daya": 44.89086540842813,
    "tegangan": 0,
    "arus": 0
  },
  {
    "waktu": "2019-01-05 00:00",
    "suhu": "24.521",
    "kelembapan": "1.138",
    "intensitas": "0",
    "daya": 42.91576636538118,
    "tegangan": 0,
    "arus": 0
  },
  {
    "waktu": "2019-01-05 01:00",
    "suhu": "24.390",
    "kelembapan": "1.138",
    "intensitas": "0",
    "daya": 41.20020945166574,
    "tegangan": 0,
    "arus": 0
  },
  {
    "waktu": "2019-01-05 02:00",
    "suhu": "24.301",
    "kelembapan": "1.138",
    "intensitas": "0",
    "daya": 43.04045152749896,
    "tegangan": 0,
    "arus": 0
  },
  {
    "waktu": "2019-01-05 03:00",
    "suhu": "24.220",
    "kelembapan": "1.139",
    "intensitas": "0",
    "daya": 44.06103277859285,
    "tegangan": 0,
    "arus": 0
  },
  {
    "waktu": "2019-01-05 04:00",
    "suhu": "24.144",
    "kelembapan": "1.139",
    "intensitas": "0",
    "daya": 40.55708723320074,
    "tegangan": 0,
    "arus": 0
  },
  {
    "waktu": "2019-01-05 05:00",
    "suhu": "24.093",
    "kelembapan": "1.140",
    "intensitas": "0",
    "daya": 41.15766102488828,
    "tegangan": 0,
    "arus": 0
  },
  {
    "waktu": "2019-01-05 06:00",
    "suhu": "24.318",
    "kelembapan": "1.140",
    "intensitas": "62.670",
    "daya": 42.52321997410156,
    "tegangan": 0,
    "arus": 0
  },
  {
    "waktu": "2019-01-05 07:00",
    "suhu": "25.299",
    "kelembapan": "1.140",
    "intensitas": "270.013",
    "daya": 44.56304331271032,
    "tegangan": 13.277149698878231,
    "arus": 3.056918975728843
  },
  {
    "waktu": "2019-01-05 08:00",
    "suhu": "26.161",
    "kelembapan": "1.138",
    "intensitas": "519.649",
    "daya": 41.62541064574259,
    "tegangan": 16.896590016752853,
    "arus": 2.4122364168667696
  },
  {
    "waktu": "2019-01-05 09:00",
    "suhu": "27.051",
    "kelembapan": "1.135",
    "intensitas": "745.446",
    "daya": 42.983117344543665,
    "tegangan": 16.890233085079842,
    "arus": 2.416582088021105
  },
  {
    "waktu": "2019-01-05 10:00",
    "suhu": "27.697",
    "kelembapan": "1.133",
    "intensitas": "897.058",
    "daya": 44.81857396678582,
    "tegangan": 17.887604752614013,
    "arus": 2.0221023439532333
  },
  {
    "waktu": "2019-01-05 11:00",
    "suhu": "28.122",
    "kelembapan": "1.130",
    "intensitas": "981.778",
    "daya": 41.928156889136325,
    "tegangan": 17.02015680824208,
    "arus": 2.1901181668002065
  },
  {
    "waktu": "2019-01-05 12:00",
    "suhu": "28.327",
    "kelembapan": "1.129",
    "intensitas": "994.434",
    "daya": 41.10893470728793,
    "tegangan": 16.916038078123446,
    "arus": 2.3027503593041976
  },
  {
    "waktu": "2019-01-05 13:00",
    "suhu": "28.305",
    "kelembapan": "1.127",
    "intensitas": "920.962",
    "daya": 44.2252304868457,
    "tegangan": 16.907908015429296,
    "arus": 2.4339665782050317
  },
  {
    "waktu": "2019-01-05 14:00",
    "suhu": "28.088",
    "kelembapan": "1.127",
    "intensitas": "784.021",
    "daya": 41.58899896823376,
    "tegangan": 16.422889754233907,
    "arus": 2.3626427814433044
  },
  {
    "waktu": "2019-01-05 15:00",
    "suhu": "27.638",
    "kelembapan": "1.127",
    "intensitas": "542.132",
    "daya": 41.04560736375501,
    "tegangan": 16.44085956537162,
    "arus": 2.426922994200337
  },
  {
    "waktu": "2019-01-05 16:00",
    "suhu": "27.042",
    "kelembapan": "1.129",
    "intensitas": "258.016",
    "daya": 44.04462731543548,
    "tegangan": 16.094314927510556,
    "arus": 2.32079569267074
  },
  {
    "waktu": "2019-01-05 17:00",
    "suhu": "26.505",
    "kelembapan": "1.131",
    "intensitas": "102.193",
    "daya": 42.240485992449905,
    "tegangan": 16.577810789324886,
    "arus": 2.355535665150267
  },
  {
    "waktu": "2019-01-05 18:00",
    "suhu": "25.972",
    "kelembapan": "1.133",
    "intensitas": "3.219",
    "daya": 44.47594468551415,
    "tegangan": 0,
    "arus": 0
  },
  {
    "waktu": "2019-01-05 19:00",
    "suhu": "25.766",
    "kelembapan": "1.134",
    "intensitas": "0",
    "daya": 41.28010378726455,
    "tegangan": 0,
    "arus": 0
  },
  {
    "waktu": "2019-01-05 20:00",
    "suhu": "25.605",
    "kelembapan": "1.135",
    "intensitas": "0",
    "daya": 43.52824691687302,
    "tegangan": 0,
    "arus": 0
  },
  {
    "waktu": "2019-01-05 21:00",
    "suhu": "25.406",
    "kelembapan": "1.135",
    "intensitas": "0",
    "daya": 44.618484436878106,
    "tegangan": 0,
    "arus": 0
  },
  {
    "waktu": "2019-01-05 22:00",
    "suhu": "25.232",
    "kelembapan": "1.136",
    "intensitas": "0",
    "daya": 42.4327714097754,
    "tegangan": 0,
    "arus": 0
  },
  {
    "waktu": "2019-01-05 23:00",
    "suhu": "25.118",
    "kelembapan": "1.136",
    "intensitas": "0",
    "daya": 40.39380760121542,
    "tegangan": 0,
    "arus": 0
  },
  {
    "waktu": "2019-01-06 00:00",
    "suhu": "24.992",
    "kelembapan": "1.135",
    "intensitas": "0",
    "daya": 44.544582665053554,
    "tegangan": 0,
    "arus": 0
  },
  {
    "waktu": "2019-01-06 01:00",
    "suhu": "24.873",
    "kelembapan": "1.135",
    "intensitas": "0",
    "daya": 41.65779808629051,
    "tegangan": 0,
    "arus": 0
  },
  {
    "waktu": "2019-01-06 02:00",
    "suhu": "24.772",
    "kelembapan": "1.135",
    "intensitas": "0",
    "daya": 40.77178872143539,
    "tegangan": 0,
    "arus": 0
  },
  {
    "waktu": "2019-01-06 03:00",
    "suhu": "24.670",
    "kelembapan": "1.135",
    "intensitas": "0",
    "daya": 42.792430514474596,
    "tegangan": 0,
    "arus": 0
  },
  {
    "waktu": "2019-01-06 04:00",
    "suhu": "24.595",
    "kelembapan": "1.136",
    "intensitas": "0",
    "daya": 42.2052781879244,
    "tegangan": 0,
    "arus": 0
  },
  {
    "waktu": "2019-01-06 05:00",
    "suhu": "24.515",
    "kelembapan": "1.137",
    "intensitas": "0",
    "daya": 42.26680847377822,
    "tegangan": 0,
    "arus": 0
  },
  {
    "waktu": "2019-01-06 06:00",
    "suhu": "24.739",
    "kelembapan": "1.138",
    "intensitas": "44.870",
    "daya": 43.40885738476656,
    "tegangan": 0,
    "arus": 0
  },
  {
    "waktu": "2019-01-06 07:00",
    "suhu": "25.350",
    "kelembapan": "1.138",
    "intensitas": "186.919",
    "daya": 42.7842887212435,
    "tegangan": 13.922162627838363,
    "arus": 2.7894952236225725
  },
  {
    "waktu": "2019-01-06 08:00",
    "suhu": "25.984",
    "kelembapan": "1.137",
    "intensitas": "338.573",
    "daya": 40.22377280127842,
    "tegangan": 16.898337185254313,
    "arus": 2.141732557235878
  },
  {
    "waktu": "2019-01-06 09:00",
    "suhu": "26.535",
    "kelembapan": "1.136",
    "intensitas": "495.974",
    "daya": 44.26816777635603,
    "tegangan": 16.886421472885196,
    "arus": 2.1688475655801813
  },
  {
    "waktu": "2019-01-06 10:00",
    "suhu": "27.153",
    "kelembapan": "1.133",
    "intensitas": "648.229",
    "daya": 40.97392213753352,
    "tegangan": 17.026345469361058,
    "arus": 2.1977353325961886
  },
  {
    "waktu": "2019-01-06 11:00",
    "suhu": "27.675",
    "kelembapan": "1.131",
    "intensitas": "741.533",
    "daya": 40.23322606383814,
    "tegangan": 17.42974508510151,
    "arus": 1.8343597733316792
  },
  {
    "waktu": "2019-01-06 12:00",
    "suhu": "27.987",
    "kelembapan": "1.129",
    "intensitas": "800.170",
    "daya": 44.17657332842075,
    "tegangan": 16.4876683185167,
    "arus": 2.54816627211763
  },
  {
    "waktu": "2019-01-06 13:00",
    "suhu": "28.116",
    "kelembapan": "1.127",
    "intensitas": "784.542",
    "daya": 40.10861708423665,
    "tegangan": 16.258918406868865,
    "arus": 2.0070847585739253
  },
  {
    "waktu": "2019-01-06 14:00",
    "suhu": "28.066",
    "kelembapan": "1.126",
    "intensitas": "692.259",
    "daya": 44.112204601220775,
    "tegangan": 16.75664865612649,
    "arus": 2.4192885782034077
  },
  {
    "waktu": "2019-01-06 15:00",
    "suhu": "27.819",
    "kelembapan": "1.126",
    "intensitas": "532.480",
    "daya": 43.87242878521447,
    "tegangan": 16.23140818641318,
    "arus": 2.279418476794425
  },
  {
    "waktu": "2019-01-06 16:00",
    "suhu": "27.324",
    "kelembapan": "1.127",
    "intensitas": "305.319",
    "daya": 42.94125208960236,
    "tegangan": 16.17408375573084,
    "arus": 2.3147407207622983
  },
  {
    "waktu": "2019-01-06 17:00",
    "suhu": "26.707",
    "kelembapan": "1.129",
    "intensitas": "113.803",
    "daya": 43.4379030455154,
    "tegangan": 16.604330720669086,
    "arus": 2.5924649194121137
  },
  {
    "waktu": "2019-01-06 18:00",
    "suhu": "26.088",
    "kelembapan": "1.132",
    "intensitas": "3.709",
    "daya": 44.1215635967769,
    "tegangan": 0,
    "arus": 0
  },
  {
    "waktu": "2019-01-06 19:00",
    "suhu": "25.830",
    "kelembapan": "1.133",
    "intensitas": "0",
    "daya": 44.70583688440816,
    "tegangan": 0,
    "arus": 0
  },
  {
    "waktu": "2019-01-06 20:00",
    "suhu": "25.688",
    "kelembapan": "1.134",
    "intensitas": "0",
    "daya": 42.56534375408678,
    "tegangan": 0,
    "arus": 0
  },
  {
    "waktu": "2019-01-06 21:00",
    "suhu": "25.534",
    "kelembapan": "1.135",
    "intensitas": "0",
    "daya": 41.90773491286595,
    "tegangan": 0,
    "arus": 0
  },
  {
    "waktu": "2019-01-06 22:00",
    "suhu": "25.355",
    "kelembapan": "1.136",
    "intensitas": "0",
    "daya": 41.77802427204325,
    "tegangan": 0,
    "arus": 0
  },
  {
    "waktu": "2019-01-06 23:00",
    "suhu": "25.146",
    "kelembapan": "1.136",
    "intensitas": "0",
    "daya": 40.65212375432005,
    "tegangan": 0,
    "arus": 0
  },
  {
    "waktu": "2019-01-07 00:00",
    "suhu": "24.942",
    "kelembapan": "1.135",
    "intensitas": "0",
    "daya": 43.067354502629755,
    "tegangan": 0,
    "arus": 0
  },
  {
    "waktu": "2019-01-07 01:00",
    "suhu": "24.721",
    "kelembapan": "1.135",
    "intensitas": "0",
    "daya": 42.004899295945194,
    "tegangan": 0,
    "arus": 0
  },
  {
    "waktu": "2019-01-07 02:00",
    "suhu": "24.509",
    "kelembapan": "1.135",
    "intensitas": "0",
    "daya": 44.858447917305696,
    "tegangan": 0,
    "arus": 0
  },
  {
    "waktu": "2019-01-07 03:00",
    "suhu": "24.344",
    "kelembapan": "1.136",
    "intensitas": "0",
    "daya": 43.08990895823153,
    "tegangan": 0,
    "arus": 0
  },
  {
    "waktu": "2019-01-07 04:00",
    "suhu": "24.252",
    "kelembapan": "1.136",
    "intensitas": "0",
    "daya": 44.274949273276654,
    "tegangan": 0,
    "arus": 0
  },
  {
    "waktu": "2019-01-07 05:00",
    "suhu": "24.217",
    "kelembapan": "1.137",
    "intensitas": "0",
    "daya": 43.79530639974654,
    "tegangan": 0,
    "arus": 0
  },
  {
    "waktu": "2019-01-07 06:00",
    "suhu": "24.550",
    "kelembapan": "1.137",
    "intensitas": "49.013",
    "daya": 43.77220979326344,
    "tegangan": 0,
    "arus": 0
  },
  {
    "waktu": "2019-01-07 07:00",
    "suhu": "25.382",
    "kelembapan": "1.137",
    "intensitas": "209.469",
    "daya": 40.0083994937889,
    "tegangan": 13.943648122657688,
    "arus": 2.400251175770857
  },
  {
    "waktu": "2019-01-07 08:00",
    "suhu": "25.951",
    "kelembapan": "1.137",
    "intensitas": "365.527",
    "daya": 40.100119720632556,
    "tegangan": 16.124818076819803,
    "arus": 2.134381085775859
  },
  {
    "waktu": "2019-01-07 09:00",
    "suhu": "26.485",
    "kelembapan": "1.135",
    "intensitas": "491.472",
    "daya": 41.183299177994435,
    "tegangan": 16.132951577622148,
    "arus": 2.3149504104889225
  },
  {
    "waktu": "2019-01-07 10:00",
    "suhu": "27.200",
    "kelembapan": "1.132",
    "intensitas": "596.212",
    "daya": 43.8144013856545,
    "tegangan": 17.45840070389,
    "arus": 2.2262352064825084
  },
  {
    "waktu": "2019-01-07 11:00",
    "suhu": "27.863",
    "kelembapan": "1.129",
    "intensitas": "671.975",
    "daya": 44.606000221258235,
    "tegangan": 17.340858480678957,
    "arus": 2.1514690323403776
  },
  {
    "waktu": "2019-01-07 12:00",
    "suhu": "28.371",
    "kelembapan": "1.126",
    "intensitas": "712.835",
    "daya": 43.18025716319855,
    "tegangan": 16.497532730452438,
    "arus": 2.402042861198999
  },
  {
    "waktu": "2019-01-07 13:00",
    "suhu": "28.311",
    "kelembapan": "1.125",
    "intensitas": "592.888",
    "daya": 41.36419792840276,
    "tegangan": 16.10768236966746,
    "arus": 2.3762111855652046
  },
  {
    "waktu": "2019-01-07 14:00",
    "suhu": "27.783",
    "kelembapan": "1.125",
    "intensitas": "403.633",
    "daya": 41.536004075559724,
    "tegangan": 16.923094243168094,
    "arus": 2.4083063088693586
  },
  {
    "waktu": "2019-01-07 15:00",
    "suhu": "27.190",
    "kelembapan": "1.127",
    "intensitas": "276.848",
    "daya": 42.31819185755569,
    "tegangan": 16.818046532693227,
    "arus": 2.4460695410851465
  },
  {
    "waktu": "2019-01-07 16:00",
    "suhu": "26.644",
    "kelembapan": "1.129",
    "intensitas": "150.195",
    "daya": 42.33133108786888,
    "tegangan": 16.475704691122047,
    "arus": 2.142830121998958
  },
  {
    "waktu": "2019-01-07 17:00",
    "suhu": "26.192",
    "kelembapan": "1.132",
    "intensitas": "50.230",
    "daya": 43.965634351056295,
    "tegangan": 16.71833415641277,
    "arus": 2.356351256970843
  },
  {
    "waktu": "2019-01-07 18:00",
    "suhu": "25.826",
    "kelembapan": "1.133",
    "intensitas": "1.676",
    "daya": 44.430918020151225,
    "tegangan": 0,
    "arus": 0
  },
  {
    "waktu": "2019-01-07 19:00",
    "suhu": "25.652",
    "kelembapan": "1.134",
    "intensitas": "0",
    "daya": 40.40090530563198,
    "tegangan": 0,
    "arus": 0
  },
  {
    "waktu": "2019-01-07 20:00",
    "suhu": "25.523",
    "kelembapan": "1.134",
    "intensitas": "0",
    "daya": 42.041191828542686,
    "tegangan": 0,
    "arus": 0
  },
  {
    "waktu": "2019-01-07 21:00",
    "suhu": "25.464",
    "kelembapan": "1.135",
    "intensitas": "0",
    "daya": 40.59207104689147,
    "tegangan": 0,
    "arus": 0
  },
  {
    "waktu": "2019-01-07 22:00",
    "suhu": "25.445",
    "kelembapan": "1.135",
    "intensitas": "0",
    "daya": 43.22824169789915,
    "tegangan": 0,
    "arus": 0
  },
  {
    "waktu": "2019-01-07 23:00",
    "suhu": "25.369",
    "kelembapan": "1.135",
    "intensitas": "0",
    "daya": 41.84530907634187,
    "tegangan": 0,
    "arus": 0
  },
  {
    "waktu": "2019-01-08 00:00",
    "suhu": "25.300",
    "kelembapan": "1.134",
    "intensitas": "0",
    "daya": 41.17973433651622,
    "tegangan": 0,
    "arus": 0
  },
  {
    "waktu": "2019-01-08 01:00",
    "suhu": "25.277",
    "kelembapan": "1.134",
    "intensitas": "0",
    "daya": 44.85188043319306,
    "tegangan": 0,
    "arus": 0
  },
  {
    "waktu": "2019-01-08 02:00",
    "suhu": "25.229",
    "kelembapan": "1.134",
    "intensitas": "0",
    "daya": 43.99462999902975,
    "tegangan": 0,
    "arus": 0
  },
  {
    "waktu": "2019-01-08 03:00",
    "suhu": "25.204",
    "kelembapan": "1.134",
    "intensitas": "0",
    "daya": 41.28628519646986,
    "tegangan": 0,
    "arus": 0
  },
  {
    "waktu": "2019-01-08 04:00",
    "suhu": "25.202",
    "kelembapan": "1.134",
    "intensitas": "0",
    "daya": 40.45011198692014,
    "tegangan": 0,
    "arus": 0
  },
  {
    "waktu": "2019-01-08 05:00",
    "suhu": "25.202",
    "kelembapan": "1.135",
    "intensitas": "0",
    "daya": 41.36796909688895,
    "tegangan": 0,
    "arus": 0
  },
  {
    "waktu": "2019-01-08 06:00",
    "suhu": "25.257",
    "kelembapan": "1.135",
    "intensitas": "22.271",
    "daya": 43.770195430673695,
    "tegangan": 0,
    "arus": 0
  }
]